{"name":"Untitled","created":"2021-08-03T19:11:22.264Z","settings":{"physics":{"gravity":[0,-9.8,0]},"render":{"fog_end":1000,"tonemapping":0,"skybox":null,"fog_density":0.01,"gamma_correction":1,"exposure":1,"fog_start":1,"global_ambient":[0.2,0.2,0.2],"skyboxIntensity":1,"fog_color":[0,0,0],"lightmapMode":1,"fog":"none","lightmapMaxResolution":2048,"skyboxMip":0,"lightmapSizeMultiplier":16,"skyboxRotation":[0,0,0],"lightmapFilterEnabled":false,"lightmapFilterRange":10,"lightmapFilterSmoothness":0.2,"ambientBake":false,"ambientBakeNumSamples":1,"ambientBakeSpherePart":0.4,"ambientBakeOcclusionBrightness":0,"ambientBakeOcclusionContrast":0,"clusteredLightingEnabled":true,"lightingCells":[10,3,10],"lightingMaxLightsPerCell":255,"lightingCookieAtlasResolution":2048,"lightingShadowAtlasResolution":2048,"lightingShadowType":0,"lightingCookiesEnabled":false,"lightingAreaLightsEnabled":false,"lightingShadowsEnabled":true,"skyType":"infinite","skyMeshPosition":[0,0,0],"skyMeshRotation":[0,0,0],"skyMeshScale":[100,100,100],"skyCenter":[0,0.1,0]}},"entities":{"!  ":{"!":"Root","#":null,"$":"!  ","%":{"O":{" ":true,"P":["iOspressFix"],"Q":{"u":{" ":true,"R":{}}}}},"&":[]," ":true,"'":["! :","! /","! ;","! #","! <","! =","! >","! ?","! @","! 0"],"___2":0},"! :":{"!":"Camera","#":"!  ","$":"! :","%":{"v":{"0":[0,0,1,1],"w":1,"x":1000,"y":true,")":[0,1,2,3,4],"z":0,"{":45,"|":true,"}":true,"~":[0.118,0.118,0.118,1]," ":true,"! ":1.94222,"!!":0.1,"!#":1,"!$":0}},"&":[]," ":true,"'":[],"___1":[51,0,6]},"! /":{"!":"horizontalMovement","&":[]," ":true,"$":"! /","#":"!  ","'":["! 1"],"%":{"O":{" ":true,"P":["playerPhysicsx"],"Q":{"!%":{" ":true,"R":{}}}}},"___2":0},"! 1":{"!":"verticalMovement","&":[]," ":true,"$":"! 1","#":"! /","'":["! 2"],"%":{"O":{" ":true,"P":["playerPhysicsy"],"Q":{"!&":{" ":true,"R":{}}}}},"___2":0},"! 2":{"!":"mainCharSprite","&":[]," ":true,"$":"! 2","#":"! 1","'":["! ,"],"%":{"h":{" ":true,"*":"animated","+":1,",":1,"-":[1,1,1],".":1,"i":false,"j":false,"(":null,"k":0,"l":1,"/":null,")":[0,1000],"m":10,"n":"jump","o":{"r":{"!":"jump","f":10,"g":false,"!'":true,"(":225743984},"s":{"!":"fallingIdle","f":10,"g":true,"(":225743983},"t":{"!":"spikeDeath","f":10,"g":false,"(":225743986}}},"O":{" ":true,"P":["mainCharAnim"],"Q":{"!(":{" ":true,"R":{}}}}},"___1":[0,0,54]},"! ,":{"!":"verticalPlayerCollision","&":[]," ":true,"$":"! ,","#":"! 2","'":["! A","! B"],"%":{},"___1":[57,0,6]},"! A":{"!":"lPlayerCollision","&":[]," ":true,"$":"! A","#":"! ,","'":[],"%":{},"___1":[60,36,39]},"! B":{"!":"rPlayerCollision","&":[]," ":true,"$":"! B","#":"! ,","'":[],"%":{},"___1":[63,36,39]},"! ;":{"!":"background","&":[]," ":true,"$":"! ;","#":"!  ","'":[],"%":{"h":{" ":true,"*":"simple","+":1,",":1,"-":[1,1,1],".":1,"i":false,"j":false,"(":52903045,"k":0,"l":1,"/":null,")":[0],"m":0,"n":null,"o":{}}},"___1":[66,0,69]},"! #":{"!":"UI","&":[]," ":true,"$":"! #","#":"!  ","'":["! C","! D","! $","! '","! *","! 3"],"%":{"!)":{" ":true,"!*":true,"!+":"blend","!,":0.5,"!-":[1000,1600],"!.":[1000,1600]}},"___2":0},"! C":{"!":"dropShadow","&":[]," ":true,"$":"! C","#":"! #","'":[],"%":{"1":{"0":[0,0,1,1],"2":[0.5,0.5,0.5,0.5],"3":[0.5,0.5],"4":"","5":null,"6":null,"7":32,"8":8,"9":32," ":true,"*":"image",":":false,";":false,"<":null,"=":32,">":true,"?":1,"-":[1,1,1],".":0.109,"@":null,"(":54713579,"A":0,"B":null,"+":1067,",":1067,"C":[-533.5,-341.243,-533.5,-725.757],"D":[0.5,0.5],"E":[0,0,0,1],"F":0,"G":[0,0,0,1],"H":[0,0],"I":null,"J":false,"K":false,"L":false,"/":null,"M":false,")":[4],"N":false}},"___1":[72,0,75]},"! D":{"!":"controlsBG","&":[]," ":true,"$":"! D","#":"! #","'":[],"%":{"1":{"0":[0,0,1,1],"2":[0.5,0.5,0.5,0.5],"3":[0.5,0.5],"4":"","5":null,"6":null,"7":32,"8":8,"9":32," ":true,"*":"image",":":false,";":false,"<":null,"=":32,">":true,"?":1,"-":[1,1,1],".":1,"@":null,"(":53197355,"A":0,"B":null,"+":1,",":1,"C":[-0.5,-609.673,-0.5,608.673],"D":[0.5,0.5],"E":[0,0,0,1],"F":0,"G":[0,0,0,1],"H":[0,0],"I":null,"J":false,"K":false,"L":false,"/":null,"M":false,")":[4],"N":false}},"___1":[78,0,81]},"! $":{"!":"score","&":[]," ":true,"$":"! $","#":"! #","'":["! E","! F","! G","! H","! I","! J"],"%":{"1":{"0":[0,0,1,1],"2":[0,1,0,1],"3":[0,1],"4":"","5":null,"6":null,"7":32,"8":8,"9":32," ":true,"*":"group",":":false,";":false,"<":null,"=":32,">":true,"?":1,"-":[1,1,1],".":1,"@":null,"(":null,"A":0,"B":null,"+":32,",":32,"C":[18.864,-55.35,-50.864,23.35],"D":[0.5,0.5],"E":[0,0,0,1],"F":0,"G":[0,0,0,1],"H":[0,0],"I":null,"J":false,"K":false,"L":false,"/":null,"M":false,")":[4],"N":false},"O":{" ":true,"P":["scoringSystem"],"Q":{"!/":{" ":true,"R":{}}}}},"___1":[84,0,6]},"! E":{"!":"ones","&":[]," ":true,"$":"! E","#":"! $","'":[],"%":{"1":{"0":[0,0,1,1],"2":[0.5,0.5,0.5,0.5],"3":[0.5,0.5],"4":"","5":null,"6":null,"7":32,"8":8,"9":32," ":true,"*":"image",":":false,";":false,"<":null,"=":32,">":true,"?":1,"-":[1,1,1],".":1,"@":null,"(":54294625,"A":0,"B":null,"+":11,",":15,"C":[244.5,-7.5,-255.5,-7.5],"D":[0.5,0.5],"E":[0,0,0,1],"F":0,"G":[0,0,0,1],"H":[0,0],"I":null,"J":false,"K":false,"L":false,"/":null,"M":false,")":[4],"N":false}},"___1":[12,0,3]},"! F":{"!":"tens","&":[]," ":true,"$":"! F","#":"! $","'":[],"%":{"1":{"0":[0,0,1,1],"2":[0.5,0.5,0.5,0.5],"3":[0.5,0.5],"4":"","5":null,"6":null,"7":32,"8":8,"9":32," ":true,"*":"image",":":false,";":false,"<":null,"=":32,">":true,"?":1,"-":[1,1,1],".":1,"@":null,"(":54294625,"A":0,"B":null,"+":11,",":15,"C":[194.5,-7.5,-205.5,-7.5],"D":[0.5,0.5],"E":[0,0,0,1],"F":0,"G":[0,0,0,1],"H":[0,0],"I":null,"J":false,"K":false,"L":false,"/":null,"M":false,")":[4],"N":false}},"___1":[15,0,3]},"! G":{"!":"hundreds","&":[]," ":true,"$":"! G","#":"! $","'":[],"%":{"1":{"0":[0,0,1,1],"2":[0.5,0.5,0.5,0.5],"3":[0.5,0.5],"4":"","5":null,"6":null,"7":32,"8":8,"9":32," ":true,"*":"image",":":false,";":false,"<":null,"=":32,">":true,"?":1,"-":[1,1,1],".":1,"@":null,"(":54294625,"A":0,"B":null,"+":11,",":15,"C":[144.5,-7.5,-155.5,-7.5],"D":[0.5,0.5],"E":[0,0,0,1],"F":0,"G":[0,0,0,1],"H":[0,0],"I":null,"J":false,"K":false,"L":false,"/":null,"M":false,")":[4],"N":false}},"___1":[18,0,3]},"! H":{"!":"thousands","&":[]," ":true,"$":"! H","#":"! $","'":[],"%":{"1":{"0":[0,0,1,1],"2":[0.5,0.5,0.5,0.5],"3":[0.5,0.5],"4":"","5":null,"6":null,"7":32,"8":8,"9":32," ":true,"*":"image",":":false,";":false,"<":null,"=":32,">":true,"?":1,"-":[1,1,1],".":1,"@":null,"(":54294625,"A":0,"B":null,"+":11,",":15,"C":[94.5,-7.5,-105.5,-7.5],"D":[0.5,0.5],"E":[0,0,0,1],"F":0,"G":[0,0,0,1],"H":[0,0],"I":null,"J":false,"K":false,"L":false,"/":null,"M":false,")":[4],"N":false}},"___1":[21,0,3]},"! I":{"!":"tenthousands","&":[]," ":true,"$":"! I","#":"! $","'":[],"%":{"1":{"0":[0,0,1,1],"2":[0.5,0.5,0.5,0.5],"3":[0.5,0.5],"4":"","5":null,"6":null,"7":32,"8":8,"9":32," ":true,"*":"image",":":false,";":false,"<":null,"=":32,">":true,"?":1,"-":[1,1,1],".":1,"@":null,"(":54294625,"A":0,"B":null,"+":11,",":15,"C":[44.5,-7.5,-55.5,-7.5],"D":[0.5,0.5],"E":[0,0,0,1],"F":0,"G":[0,0,0,1],"H":[0,0],"I":null,"J":false,"K":false,"L":false,"/":null,"M":false,")":[4],"N":false}},"___1":[24,0,3]},"! J":{"!":"onehundredthousands","&":[]," ":true,"$":"! J","#":"! $","'":[],"%":{"1":{"0":[0,0,1,1],"2":[0.5,0.5,0.5,0.5],"3":[0.5,0.5],"4":"","5":null,"6":null,"7":32,"8":8,"9":32," ":true,"*":"image",":":false,";":false,"<":null,"=":32,">":true,"?":1,"-":[1,1,1],".":1,"@":null,"(":54294625,"A":0,"B":null,"+":11,",":15,"C":[-5.5,-7.5,-5.5,-7.5],"D":[0.5,0.5],"E":[0,0,0,1],"F":0,"G":[0,0,0,1],"H":[0,0],"I":null,"J":false,"K":false,"L":false,"/":null,"M":false,")":[4],"N":false}},"___1":[0,0,3]},"! '":{"!":"deathScreenDropDown","&":[]," ":true,"$":"! '","#":"! #","'":["! K","! L","! M","! N","! ("],"%":{"1":{"0":[0,0,1,1],"2":[0.5,0.5,0.5,0.5],"3":[0.5,0.5],"4":"","5":null,"6":null,"7":32,"8":8,"9":32," ":true,"*":"group",":":false,";":false,"<":null,"=":32,">":true,"?":1,"-":[1,1,1],".":1,"@":null,"(":null,"A":0,"B":null,"+":32,",":32,"C":[-16,1284,-16,-1316],"D":[0.5,0.5],"E":[0,0,0,1],"F":0,"G":[0,0,0,1],"H":[0,0],"I":null,"J":false,"K":false,"L":false,"/":null,"M":false,")":[4],"N":false},"O":{" ":true,"P":["deathScreenDropDown"],"Q":{"!0":{" ":true,"R":{}}}}},"___1":[87,0,6]},"! K":{"!":"background","&":[]," ":true,"$":"! K","#":"! '","'":[],"%":{"1":{"0":[0,0,1,1],"2":[0.5,0.5,0.5,0.5],"3":[0.5,0.5],"4":"","5":null,"6":null,"7":32,"8":8,"9":32," ":true,"*":"image",":":false,";":false,"<":null,"=":32,">":true,"?":1,"-":[1,1,1],".":1,"@":null,"(":53197355,"A":0,"B":null,"+":1,",":1,"C":[-0.5,340.802,-0.5,-341.802],"D":[0.5,0.5],"E":[0,0,0,1],"F":0,"G":[0,0,0,1],"H":[0,0],"I":null,"J":false,"K":false,"L":false,"/":null,"M":false,")":[4],"N":false}},"___1":[90,0,93]},"! L":{"!":"brandLogo","&":[]," ":true,"$":"! L","#":"! '","'":[],"%":{"1":{"0":[0,0,1,1],"2":[0.5,0.5,0.5,0.5],"3":[0.5,0.5],"4":"","5":null,"6":null,"7":32,"8":8,"9":32," ":true,"*":"image",":":false,";":false,"<":null,"=":32,">":true,"?":1,"-":[1,1,1],".":1,"@":55277018,"(":null,"A":0,"B":null,"+":1200,",":956,"C":[-600,-11.55,-600,-944.45],"D":[0.5,0.5],"E":[0,0,0,1],"F":0,"G":[0,0,0,1],"H":[0,0],"I":null,"J":false,"K":false,"L":false,"/":null,"M":false,")":[4],"N":false}},"___1":[96,0,99]},"! M":{"!":"youWin","&":[]," ":true,"$":"! M","#":"! '","'":[],"%":{"1":{"0":[0,0,1,1],"2":[0.5,0.5,0.5,0.5],"3":[0.5,0.5],"4":"","5":null,"6":null,"7":32,"8":8,"9":32," ":true,"*":"image",":":false,";":false,"<":null,"=":32,">":true,"?":1,"-":[1,1,1],".":1,"@":null,"(":54928452,"A":0,"B":null,"+":96.211,",":14,"C":[-48.108,85.772,-48.103,-99.772],"D":[0.5,0.5],"E":[0,0,0,1],"F":0,"G":[0,0,0,1],"H":[0,0],"I":null,"J":false,"K":false,"L":false,"/":null,"M":false,")":[4],"N":false}},"___1":[102,0,105]},"! N":{"!":"youLose","&":[]," ":false,"$":"! N","#":"! '","'":[],"%":{"1":{"0":[0,0,1,1],"2":[0.5,0.5,0.5,0.5],"3":[0.5,0.5],"4":"","5":null,"6":null,"7":32,"8":8,"9":32," ":true,"*":"image",":":false,";":false,"<":null,"=":32,">":true,"?":1,"-":[1,1,1],".":1,"@":null,"(":54928453,"A":0,"B":null,"+":107,",":14,"C":[-53.501,85.772,-53.499,-99.772],"D":[0.5,0.5],"E":[0,0,0,1],"F":0,"G":[0,0,0,1],"H":[0,0],"I":null,"J":false,"K":false,"L":false,"/":null,"M":false,")":[4],"N":false}},"___1":[108,0,111]},"! (":{"!":"scoreFrame","&":[]," ":true,"$":"! (","#":"! '","'":["! O","! P","! %","! &"],"%":{"1":{"0":[0,0,1,1],"2":[0.5,0.5,0.5,0.5],"3":[0.5,0.5],"4":"","5":null,"6":null,"7":32,"8":8,"9":32," ":true,"*":"image",":":false,";":false,"<":null,"=":32,">":true,"?":1,"-":[1,1,1],".":1,"@":null,"(":77088919,"A":0,"B":null,"+":69.219,",":29,"C":[-31,-211.87,-31,182.87],"D":[0.5,0.5],"E":[0,0,0,1],"F":0,"G":[0,0,0,1],"H":[0,0],"I":null,"J":false,"K":false,"L":false,"/":null,"M":false,")":[4],"N":false}},"___1":[114,0,117]},"! O":{"!":"scoretext","&":[]," ":true,"$":"! O","#":"! (","'":[],"%":{"1":{"0":[0,0,1,1],"2":[0.5,0.5,0.5,0.5],"3":[0.5,0.5],"4":"","5":null,"6":null,"7":32,"8":8,"9":32," ":true,"*":"image",":":false,";":false,"<":null,"=":32,">":true,"?":1,"-":[1,1,1],".":1,"@":null,"(":55073645,"A":0,"B":null,"+":29,",":5,"C":[-26.954,0.669,-2.046,-5.669],"D":[0.5,0.5],"E":[0,0,0,1],"F":0,"G":[0,0,0,1],"H":[0,0],"I":null,"J":false,"K":false,"L":false,"/":null,"M":false,")":[4],"N":false}},"___1":[120,0,123]},"! P":{"!":"highscoretext","&":[]," ":true,"$":"! P","#":"! (","'":[],"%":{"1":{"0":[0,0,1,1],"2":[0.5,0.5,0.5,0.5],"3":[0.5,0.5],"4":"","5":null,"6":null,"7":32,"8":8,"9":32," ":true,"*":"image",":":false,";":false,"<":null,"=":32,">":true,"?":1,"-":[1,1,1],".":1,"@":null,"(":55073646,"A":0,"B":null,"+":53,",":8,"C":[-38.534,-7.907,-14.466,-0.093],"D":[0.5,0.5],"E":[0,0,0,1],"F":0,"G":[0,0,0,1],"H":[0,0],"I":null,"J":false,"K":false,"L":false,"/":null,"M":false,")":[4],"N":false}},"___1":[126,0,129]},"! %":{"!":"endGameScore","&":[]," ":true,"$":"! %","#":"! (","'":["! Q","! R","! S","! T","! U","! V"],"%":{"1":{"0":[0,0,1,1],"2":[0,1,0,1],"3":[0,1],"4":"","5":null,"6":null,"7":32,"8":8,"9":32," ":true,"*":"group",":":false,";":false,"<":null,"=":32,">":true,"?":1,"-":[1,1,1],".":1,"@":null,"(":null,"A":0,"B":null,"+":32,",":32,"C":[33.038,-41.652,-65.038,9.652],"D":[0.5,0.5],"E":[0,0,0,1],"F":0,"G":[0,0,0,1],"H":[0,0],"I":null,"J":false,"K":false,"L":false,"/":null,"M":false,")":[4],"N":false},"O":{" ":true,"P":["endScreenScore"],"Q":{"!1":{" ":true,"R":{}}}}},"___1":[132,0,42]},"! Q":{"!":"ones","&":[]," ":true,"$":"! Q","#":"! %","'":[],"%":{"1":{"0":[0,0,1,1],"2":[0.5,0.5,0.5,0.5],"3":[0.5,0.5],"4":"","5":null,"6":null,"7":32,"8":8,"9":32," ":true,"*":"image",":":false,";":false,"<":null,"=":32,">":true,"?":1,"-":[1,1,1],".":1,"@":null,"(":54294625,"A":0,"B":null,"+":11,",":15,"C":[244.5,-7.5,-255.5,-7.5],"D":[0.5,0.5],"E":[0,0,0,1],"F":0,"G":[0,0,0,1],"H":[0,0],"I":null,"J":false,"K":false,"L":false,"/":null,"M":false,")":[4],"N":false}},"___1":[12,0,3]},"! R":{"!":"tens","&":[]," ":true,"$":"! R","#":"! %","'":[],"%":{"1":{"0":[0,0,1,1],"2":[0.5,0.5,0.5,0.5],"3":[0.5,0.5],"4":"","5":null,"6":null,"7":32,"8":8,"9":32," ":true,"*":"image",":":false,";":false,"<":null,"=":32,">":true,"?":1,"-":[1,1,1],".":1,"@":null,"(":54294625,"A":0,"B":null,"+":11,",":15,"C":[194.5,-7.5,-205.5,-7.5],"D":[0.5,0.5],"E":[0,0,0,1],"F":0,"G":[0,0,0,1],"H":[0,0],"I":null,"J":false,"K":false,"L":false,"/":null,"M":false,")":[4],"N":false}},"___1":[15,0,3]},"! S":{"!":"hundreds","&":[]," ":true,"$":"! S","#":"! %","'":[],"%":{"1":{"0":[0,0,1,1],"2":[0.5,0.5,0.5,0.5],"3":[0.5,0.5],"4":"","5":null,"6":null,"7":32,"8":8,"9":32," ":true,"*":"image",":":false,";":false,"<":null,"=":32,">":true,"?":1,"-":[1,1,1],".":1,"@":null,"(":54294625,"A":0,"B":null,"+":11,",":15,"C":[144.5,-7.5,-155.5,-7.5],"D":[0.5,0.5],"E":[0,0,0,1],"F":0,"G":[0,0,0,1],"H":[0,0],"I":null,"J":false,"K":false,"L":false,"/":null,"M":false,")":[4],"N":false}},"___1":[18,0,3]},"! T":{"!":"thousands","&":[]," ":true,"$":"! T","#":"! %","'":[],"%":{"1":{"0":[0,0,1,1],"2":[0.5,0.5,0.5,0.5],"3":[0.5,0.5],"4":"","5":null,"6":null,"7":32,"8":8,"9":32," ":true,"*":"image",":":false,";":false,"<":null,"=":32,">":true,"?":1,"-":[1,1,1],".":1,"@":null,"(":54294625,"A":0,"B":null,"+":11,",":15,"C":[94.5,-7.5,-105.5,-7.5],"D":[0.5,0.5],"E":[0,0,0,1],"F":0,"G":[0,0,0,1],"H":[0,0],"I":null,"J":false,"K":false,"L":false,"/":null,"M":false,")":[4],"N":false}},"___1":[21,0,3]},"! U":{"!":"tenthousands","&":[]," ":true,"$":"! U","#":"! %","'":[],"%":{"1":{"0":[0,0,1,1],"2":[0.5,0.5,0.5,0.5],"3":[0.5,0.5],"4":"","5":null,"6":null,"7":32,"8":8,"9":32," ":true,"*":"image",":":false,";":false,"<":null,"=":32,">":true,"?":1,"-":[1,1,1],".":1,"@":null,"(":54294625,"A":0,"B":null,"+":11,",":15,"C":[44.5,-7.5,-55.5,-7.5],"D":[0.5,0.5],"E":[0,0,0,1],"F":0,"G":[0,0,0,1],"H":[0,0],"I":null,"J":false,"K":false,"L":false,"/":null,"M":false,")":[4],"N":false}},"___1":[24,0,3]},"! V":{"!":"onehundredthousands","&":[]," ":true,"$":"! V","#":"! %","'":[],"%":{"1":{"0":[0,0,1,1],"2":[0.5,0.5,0.5,0.5],"3":[0.5,0.5],"4":"","5":null,"6":null,"7":32,"8":8,"9":32," ":true,"*":"image",":":false,";":false,"<":null,"=":32,">":true,"?":1,"-":[1,1,1],".":1,"@":null,"(":54294625,"A":0,"B":null,"+":11,",":15,"C":[-5.5,-7.5,-5.5,-7.5],"D":[0.5,0.5],"E":[0,0,0,1],"F":0,"G":[0,0,0,1],"H":[0,0],"I":null,"J":false,"K":false,"L":false,"/":null,"M":false,")":[4],"N":false}},"___1":[0,0,3]},"! &":{"!":"endGameHighScore","&":[]," ":true,"$":"! &","#":"! (","'":["! W","! X","! Y","! Z","! [","! ]"],"%":{"1":{"0":[0,0,1,1],"2":[0,1,0,1],"3":[0,1],"4":"","5":null,"6":null,"7":32,"8":8,"9":32," ":true,"*":"group",":":false,";":false,"<":null,"=":32,">":true,"?":1,"-":[1,1,1],".":1,"@":null,"(":null,"A":0,"B":null,"+":32,",":32,"C":[38.635,-49.137,-70.635,17.137],"D":[0.5,0.5],"E":[0,0,0,1],"F":0,"G":[0,0,0,1],"H":[0,0],"I":null,"J":false,"K":false,"L":false,"/":null,"M":false,")":[4],"N":false},"O":{" ":true,"P":["endScreenHighScore"],"Q":{"!2":{" ":true,"R":{}}}}},"___1":[135,0,42]},"! W":{"!":"ones","&":[]," ":true,"$":"! W","#":"! &","'":[],"%":{"1":{"0":[0,0,1,1],"2":[0.5,0.5,0.5,0.5],"3":[0.5,0.5],"4":"","5":null,"6":null,"7":32,"8":8,"9":32," ":true,"*":"image",":":false,";":false,"<":null,"=":32,">":true,"?":1,"-":[1,1,1],".":1,"@":null,"(":54294625,"A":0,"B":null,"+":11,",":15,"C":[244.5,-7.5,-255.5,-7.5],"D":[0.5,0.5],"E":[0,0,0,1],"F":0,"G":[0,0,0,1],"H":[0,0],"I":null,"J":false,"K":false,"L":false,"/":null,"M":false,")":[4],"N":false}},"___1":[12,0,3]},"! X":{"!":"tens","&":[]," ":true,"$":"! X","#":"! &","'":[],"%":{"1":{"0":[0,0,1,1],"2":[0.5,0.5,0.5,0.5],"3":[0.5,0.5],"4":"","5":null,"6":null,"7":32,"8":8,"9":32," ":true,"*":"image",":":false,";":false,"<":null,"=":32,">":true,"?":1,"-":[1,1,1],".":1,"@":null,"(":54294625,"A":0,"B":null,"+":11,",":15,"C":[194.5,-7.5,-205.5,-7.5],"D":[0.5,0.5],"E":[0,0,0,1],"F":0,"G":[0,0,0,1],"H":[0,0],"I":null,"J":false,"K":false,"L":false,"/":null,"M":false,")":[4],"N":false}},"___1":[15,0,3]},"! Y":{"!":"hundreds","&":[]," ":true,"$":"! Y","#":"! &","'":[],"%":{"1":{"0":[0,0,1,1],"2":[0.5,0.5,0.5,0.5],"3":[0.5,0.5],"4":"","5":null,"6":null,"7":32,"8":8,"9":32," ":true,"*":"image",":":false,";":false,"<":null,"=":32,">":true,"?":1,"-":[1,1,1],".":1,"@":null,"(":54294625,"A":0,"B":null,"+":11,",":15,"C":[144.5,-7.5,-155.5,-7.5],"D":[0.5,0.5],"E":[0,0,0,1],"F":0,"G":[0,0,0,1],"H":[0,0],"I":null,"J":false,"K":false,"L":false,"/":null,"M":false,")":[4],"N":false}},"___1":[18,0,3]},"! Z":{"!":"thousands","&":[]," ":true,"$":"! Z","#":"! &","'":[],"%":{"1":{"0":[0,0,1,1],"2":[0.5,0.5,0.5,0.5],"3":[0.5,0.5],"4":"","5":null,"6":null,"7":32,"8":8,"9":32," ":true,"*":"image",":":false,";":false,"<":null,"=":32,">":true,"?":1,"-":[1,1,1],".":1,"@":null,"(":54294625,"A":0,"B":null,"+":11,",":15,"C":[94.5,-7.5,-105.5,-7.5],"D":[0.5,0.5],"E":[0,0,0,1],"F":0,"G":[0,0,0,1],"H":[0,0],"I":null,"J":false,"K":false,"L":false,"/":null,"M":false,")":[4],"N":false}},"___1":[21,0,3]},"! [":{"!":"tenthousands","&":[]," ":true,"$":"! [","#":"! &","'":[],"%":{"1":{"0":[0,0,1,1],"2":[0.5,0.5,0.5,0.5],"3":[0.5,0.5],"4":"","5":null,"6":null,"7":32,"8":8,"9":32," ":true,"*":"image",":":false,";":false,"<":null,"=":32,">":true,"?":1,"-":[1,1,1],".":1,"@":null,"(":54294625,"A":0,"B":null,"+":11,",":15,"C":[44.5,-7.5,-55.5,-7.5],"D":[0.5,0.5],"E":[0,0,0,1],"F":0,"G":[0,0,0,1],"H":[0,0],"I":null,"J":false,"K":false,"L":false,"/":null,"M":false,")":[4],"N":false}},"___1":[24,0,3]},"! ]":{"!":"onehundredthousands","&":[]," ":true,"$":"! ]","#":"! &","'":[],"%":{"1":{"0":[0,0,1,1],"2":[0.5,0.5,0.5,0.5],"3":[0.5,0.5],"4":"","5":null,"6":null,"7":32,"8":8,"9":32," ":true,"*":"image",":":false,";":false,"<":null,"=":32,">":true,"?":1,"-":[1,1,1],".":1,"@":null,"(":54294625,"A":0,"B":null,"+":11,",":15,"C":[-5.5,-7.5,-5.5,-7.5],"D":[0.5,0.5],"E":[0,0,0,1],"F":0,"G":[0,0,0,1],"H":[0,0],"I":null,"J":false,"K":false,"L":false,"/":null,"M":false,")":[4],"N":false}},"___1":[0,0,3]},"! *":{"!":"bottomBarButtons","&":[]," ":true,"$":"! *","#":"! #","'":["! +","! !","! -"],"%":{},"___2":0},"! +":{"!":"deathGroup","&":[]," ":true,"$":"! +","#":"! *","'":["! 4","! 5","! 6"],"%":{"1":{"0":[0,0,1,1],"2":[0.5,0.5,0.5,0.5],"3":[0.5,0.5],"4":"","5":null,"6":null,"7":32,"8":8,"9":32," ":true,"*":"group",":":false,";":false,"<":null,"=":32,">":true,"?":1,"-":[1,1,1],".":1,"@":null,"(":null,"A":0,"B":null,"+":32,",":32,"C":[984,-16,-1016,-16],"D":[0.5,0.5],"E":[0,0,0,1],"F":0,"G":[0,0,0,1],"H":[0,0],"I":null,"J":false,"K":false,"L":false,"/":null,"M":false,")":[4],"N":false},"O":{" ":true,"P":["loseGroup"],"Q":{"!3":{" ":true,"R":{}}}}},"___1":[45,0,27]},"! 4":{"!":"soloResetButton","&":[]," ":true,"$":"! 4","#":"! +","'":[],"%":{"1":{"0":[0,0,1,1],"2":[0.5,0.5,0.5,0.5],"3":[0.5,0.5],"4":"","5":null,"6":null,"7":32,"8":8,"9":32," ":true,"*":"image",":":false,";":false,"<":null,"=":32,">":true,"?":1,"-":[1,1,1],".":1,"@":null,"(":54708490,"A":0,"B":null,"+":61,",":28,"C":[-30.5,-33.486,-30.5,5.486],"D":[0.5,0.5],"E":[0,0,0,1],"F":0,"G":[0,0,0,1],"H":[0,0],"I":null,"J":false,"K":false,"L":true,"/":null,"M":false,")":[4],"N":false},"S":{" ":true,"T":true,"U":"! 4","V":[0,0,0,0],"W":1,"X":[1,1,1,1],"Y":[1,1,1,1],"Z":[1,1,1,1],"[":0,"]":54708490,"^":0,"_":54708491,"`":0,"a":54708490,"b":0,"c":null,"d":null,"e":null},"O":{" ":true,"P":["resetButton"],"Q":{"p":{" ":true,"R":{}}}}},"___1":[138,0,30]},"! 5":{"!":"claimCouponButton","&":[]," ":true,"$":"! 5","#":"! +","'":[],"%":{"1":{"0":[0,0,1,1],"2":[0.5,0.5,0.5,0.5],"3":[0.5,0.5],"4":"","5":null,"6":null,"7":32,"8":8,"9":32," ":true,"*":"image",":":false,";":false,"<":null,"=":32,">":true,"?":1,"-":[1,1,1],".":1,"@":null,"(":54708488,"A":0,"B":null,"+":61,",":28,"C":[-37.66,-33.4859,-23.34,5.4859],"D":[0.5,0.5],"E":[0,0,0,1],"F":0,"G":[0,0,0,1],"H":[0,0],"I":null,"J":false,"K":false,"L":true,"/":null,"M":false,")":[4],"N":false},"S":{" ":true,"T":true,"U":"! 5","V":[0,0,0,0],"W":1,"X":[1,1,1,1],"Y":[1,1,1,1],"Z":[1,1,1,1],"[":0,"]":54708488,"^":0,"_":54708489,"`":0,"a":54708488,"b":0,"c":null,"d":null,"e":null},"O":{" ":true,"P":["claimButton"],"Q":{"q":{" ":true,"R":{}}}}},"___1":[141,0,30]},"! 6":{"!":"resetButton","&":[]," ":true,"$":"! 6","#":"! +","'":[],"%":{"1":{"0":[0,0,1,1],"2":[0.5,0.5,0.5,0.5],"3":[0.5,0.5],"4":"","5":null,"6":null,"7":32,"8":8,"9":32," ":true,"*":"image",":":false,";":false,"<":null,"=":32,">":true,"?":1,"-":[1,1,1],".":1,"@":null,"(":54708490,"A":0,"B":null,"+":61,",":28,"C":[-23.34,-33.4859,-37.66,5.4859],"D":[0.5,0.5],"E":[0,0,0,1],"F":0,"G":[0,0,0,1],"H":[0,0],"I":null,"J":false,"K":false,"L":true,"/":null,"M":false,")":[4],"N":false},"S":{" ":true,"T":true,"U":"! 6","V":[0,0,0,0],"W":1,"X":[1,1,1,1],"Y":[1,1,1,1],"Z":[1,1,1,1],"[":0,"]":54708490,"^":0,"_":54708491,"`":0,"a":54708490,"b":0,"c":null,"d":null,"e":null},"O":{" ":true,"P":["resetButton"],"Q":{"p":{" ":true,"R":{}}}}},"___1":[144,0,147]},"! !":{"!":"startGroup","&":[]," ":true,"$":"! !","#":"! *","'":["! 7","! ^","! _","! `","! a","! b","! )"],"%":{"1":{"0":[0,0,1,1],"2":[0.5,0.5,0.5,0.5],"3":[0.5,0.5],"4":"","5":null,"6":null,"7":32,"8":8,"9":32," ":true,"*":"group",":":false,";":false,"<":null,"=":32,">":true,"?":1,"-":[1,1,1],".":1,"@":null,"(":null,"A":0,"B":null,"+":32,",":32,"C":[-16,-16,-16,-16],"D":[0.5,0.5],"E":[0,0,0,1],"F":0,"G":[0,0,0,1],"H":[0,0],"I":null,"J":false,"K":false,"L":false,"/":null,"M":false,")":[4],"N":false},"O":{" ":true,"P":["startGroup"],"Q":{"!4":{" ":true,"R":{}}}}},"___1":[0,0,27]},"! 7":{"!":"startButton","&":[]," ":true,"$":"! 7","#":"! !","'":[],"%":{"1":{"0":[0,0,1,1],"2":[0.5,0.5,0.5,0.5],"3":[0.5,0.5],"4":"","5":null,"6":null,"7":32,"8":8,"9":32," ":true,"*":"image",":":false,";":false,"<":null,"=":32,">":true,"?":1,"-":[1,1,1],".":1,"@":null,"(":54708478,"A":0,"B":null,"+":61,",":28,"C":[-30.5,-31.346,-30.5,3.346],"D":[0.5,0.5],"E":[0,0,0,1],"F":0,"G":[0,0,0,1],"H":[0,0],"I":null,"J":false,"K":false,"L":true,"/":null,"M":false,")":[4],"N":false},"S":{" ":true,"T":true,"U":"! 7","V":[0,0,0,0],"W":1,"X":[1,1,1,1],"Y":[1,1,1,1],"Z":[1,1,1,1],"[":0,"]":54708478,"^":0,"_":54708485,"`":0,"a":54708478,"b":0,"c":null,"d":null,"e":null},"O":{" ":true,"P":["startButton"],"Q":{"!5":{" ":true,"R":{}}}}},"___1":[150,0,30]},"! ^":{"!":"trampolines","&":[]," ":true,"$":"! ^","#":"! !","'":[],"%":{"1":{"0":[0,0,1,1],"2":[0.5,0.5,0.5,0.5],"3":[0.5,0.5],"4":"","5":null,"6":null,"7":32,"8":8,"9":32," ":true,"*":"image",":":false,";":false,"<":null,"=":32,">":true,"?":1,"-":[1,1,1],".":1,"@":null,"(":54928616,"A":0,"B":null,"+":59,",":8,"C":[-31.65,-27.876,-27.35,19.876],"D":[0.5,0.5],"E":[0,0,0,1],"F":0,"G":[0,0,0,1],"H":[0,0],"I":null,"J":false,"K":false,"L":false,"/":null,"M":false,")":[4],"N":false}},"___1":[153,0,9]},"! _":{"!":"avoid spikes","&":[]," ":true,"$":"! _","#":"! !","'":[],"%":{"1":{"0":[0,0,1,1],"2":[0.5,0.5,0.5,0.5],"3":[0.5,0.5],"4":"","5":null,"6":null,"7":32,"8":8,"9":32," ":true,"*":"image",":":false,";":false,"<":null,"=":32,">":true,"?":1,"-":[1,1,1],".":1,"@":null,"(":54928588,"A":0,"B":null,"+":61,",":8,"C":[-22.762,-27.885,-38.238,19.885],"D":[0.5,0.5],"E":[0,0,0,1],"F":0,"G":[0,0,0,1],"H":[0,0],"I":null,"J":false,"K":false,"L":false,"/":null,"M":false,")":[4],"N":false}},"___1":[156,0,9]},"! `":{"!":"jump up to","&":[]," ":true,"$":"! `","#":"! !","'":[],"%":{"1":{"0":[0,0,1,1],"2":[0.5,0.5,0.5,0.5],"3":[0.5,0.5],"4":"","5":null,"6":null,"7":32,"8":8,"9":32," ":true,"*":"image",":":false,";":false,"<":null,"=":32,">":true,"?":1,"-":[1,1,1],".":1,"@":null,"(":54997078,"A":0,"B":null,"+":52,",":8,"C":[-30.449,-25.864,-21.551,17.864],"D":[0.5,0.5],"E":[0,0,0,1],"F":0,"G":[0,0,0,1],"H":[0,0],"I":null,"J":false,"K":false,"L":false,"/":null,"M":false,")":[4],"N":false}},"___1":[159,0,9]},"! a":{"!":"score points","&":[]," ":true,"$":"! a","#":"! !","'":[],"%":{"1":{"0":[0,0,1,1],"2":[0.5,0.5,0.5,0.5],"3":[0.5,0.5],"4":"","5":null,"6":null,"7":32,"8":8,"9":32," ":true,"*":"image",":":false,";":false,"<":null,"=":32,">":true,"?":1,"-":[1,1,1],".":1,"@":null,"(":54997080,"A":0,"B":null,"+":61,",":8,"C":[-26.267,-25.866,-34.733,17.866],"D":[0.5,0.5],"E":[0,0,0,1],"F":0,"G":[0,0,0,1],"H":[0,0],"I":null,"J":false,"K":false,"L":false,"/":null,"M":false,")":[4],"N":false}},"___1":[162,0,9]},"! b":{"!":"hop on","&":[]," ":true,"$":"! b","#":"! !","'":[],"%":{"1":{"0":[0,0,1,1],"2":[0.5,0.5,0.5,0.5],"3":[0.5,0.5],"4":"","5":null,"6":null,"7":32,"8":8,"9":32," ":true,"*":"image",":":false,";":false,"<":null,"=":32,">":true,"?":1,"-":[1,1,1],".":1,"@":null,"(":54928615,"A":0,"B":null,"+":32,",":8,"C":[-25.304,-27.878,-6.696,19.878],"D":[0.5,0.5],"E":[0,0,0,1],"F":0,"G":[0,0,0,1],"H":[0,0],"I":null,"J":false,"K":false,"L":false,"/":null,"M":false,")":[4],"N":false}},"___1":[165,0,9]},"! )":{"!":"frontCard","&":[]," ":true,"$":"! )","#":"! !","'":["! c","! d","! e","! f"],"%":{"1":{"0":[0,0,1,1],"2":[0.5,0.5,0.5,0.5],"3":[0.5,0.5],"4":"","5":null,"6":null,"7":32,"8":8,"9":32," ":true,"*":"image",":":false,";":false,"<":null,"=":32,">":true,"?":1,"-":[1,1,1],".":1,"@":null,"(":54928623,"A":0,"B":null,"+":64,",":29,"C":[-39.83,5.14,-24.17,-34.14],"D":[0.5,0.5],"E":[0,0,0,1],"F":0,"G":[0,0,0,1],"H":[0,0],"I":null,"J":false,"K":false,"L":false,"/":null,"M":false,")":[4],"N":false}},"___1":[168,0,171]},"! c":{"!":"Image","&":[]," ":true,"$":"! c","#":"! )","'":[],"%":{"1":{"0":[0,0,1,1],"2":[0.5,0.5,0.5,0.5],"3":[0.5,0.5],"4":"","5":null,"6":null,"7":32,"8":8,"9":32," ":true,"*":"image",":":false,";":false,"<":null,"=":32,">":true,"?":1,"-":[1,1,1],".":1,"@":55277018,"(":null,"A":0,"B":null,"+":1200,",":956,"C":[-619.221,-477.346,-580.779,-478.654],"D":[0.5,0.5],"E":[0,0,0,1],"F":0,"G":[0,0,0,1],"H":[0,0],"I":null,"J":false,"K":false,"L":false,"/":null,"M":false,")":[4],"N":false}},"___1":[174,0,177]},"! -":{"!":"LRGroup","&":[]," ":true,"$":"! -","#":"! *","'":["! 8","! 9"],"%":{"1":{"0":[0,0,1,1],"2":[0.5,0.5,0.5,0.5],"3":[0.5,0.5],"4":"","5":null,"6":null,"7":32,"8":8,"9":32," ":true,"*":"group",":":false,";":false,"<":null,"=":32,">":true,"?":1,"-":[1,1,1],".":1,"@":null,"(":null,"A":0,"B":null,"+":32,",":32,"C":[984,-16,-1016,-16],"D":[0.5,0.5],"E":[0,0,0,1],"F":0,"G":[0,0,0,1],"H":[0,0],"I":null,"J":false,"K":false,"L":false,"/":null,"M":false,")":[4],"N":false},"O":{" ":true,"P":["leftRightGroup"],"Q":{"!6":{" ":true,"R":{}}}}},"___1":[45,0,27]},"! 8":{"!":"LButton","&":[]," ":true,"$":"! 8","#":"! -","'":[],"%":{"1":{"0":[0,0,1,1],"2":[0,0,0,0],"3":[0,0],"4":"","5":null,"6":null,"7":32,"8":8,"9":32," ":true,"*":"image",":":false,";":false,"<":null,"=":32,">":true,"?":1,"-":[1,1,1],".":1,"@":null,"(":54708444,"A":0,"B":null,"+":39,",":41,"C":[3.353,-8.703,-42.353,-32.297],"D":[0.5,0.5],"E":[0,0,0,1],"F":0,"G":[0,0,0,1],"H":[0,0],"I":null,"J":false,"K":false,"L":true,"/":null,"M":false,")":[4],"N":false},"S":{" ":true,"T":true,"U":"! 8","V":[0,0,0,0],"W":1,"X":[1,1,1,1],"Y":[1,1,1,0.58824],"Z":[1,1,1,1],"[":20,"]":54708444,"^":0,"_":54708450,"`":0,"a":54708444,"b":0,"c":null,"d":null,"e":null},"O":{" ":true,"P":["moveLeftButton"],"Q":{"!7":{" ":true,"R":{}}}}},"___1":[180,0,183]},"! 9":{"!":"RButton","&":[]," ":true,"$":"! 9","#":"! -","'":[],"%":{"1":{"0":[0,0,1,1],"2":[1,0,1,0],"3":[1,0],"4":"","5":null,"6":null,"7":32,"8":8,"9":32," ":true,"*":"image",":":false,";":false,"<":null,"=":32,">":true,"?":1,"-":[1,1,1],".":1,"@":null,"(":54708451,"A":0,"B":null,"+":39,",":41,"C":[-42.461,-8.703,3.461,-32.297],"D":[0.5,0.5],"E":[0,0,0,1],"F":0,"G":[0,0,0,1],"H":[0,0],"I":null,"J":false,"K":false,"L":true,"/":null,"M":false,")":[4],"N":false},"S":{" ":true,"T":true,"U":"! 9","V":[0,0,0,0],"W":1,"X":[1,1,1,1],"Y":[1,1,1,0.58824],"Z":[1,1,1,1],"[":20,"]":54708451,"^":0,"_":54708477,"`":0,"a":54708451,"b":0,"c":null,"d":null,"e":null},"O":{" ":true,"P":["moveRightButton"],"Q":{"!8":{" ":true,"R":{}}}}},"___1":[186,0,189]},"! 3":{"!":"couponNotification","&":[]," ":true,"$":"! 3","#":"! #","'":["! ."],"%":{"1":{"0":[0,0,1,1],"2":[0.5,0.5,0.5,0.5],"3":[0.5,0.5],"4":"","5":null,"6":null,"7":32,"8":8,"9":32," ":true,"*":"group",":":false,";":false,"<":null,"=":32,">":true,"?":1,"-":[1,1,1],".":1,"@":null,"(":null,"A":0,"B":null,"+":32,",":32,"C":[-16,87.62,-16,-119.62],"D":[0.5,0.5],"E":[0,0,0,1],"F":0,"G":[0,0,0,1],"H":[0,0],"I":null,"J":false,"K":false,"L":false,"/":null,"M":false,")":[4],"N":false},"O":{" ":true,"P":["couponNotification"],"Q":{"!9":{" ":true,"R":{}}}}},"___1":[192,0,6]},"! .":{"!":"notificationBG","&":[]," ":true,"$":"! .","#":"! 3","'":["! g"],"%":{"1":{"0":[0,0,1,1],"2":[0.5,0.5,0.5,0.5],"3":[0.5,0.5],"4":"","5":null,"6":null,"7":32,"8":8,"9":32," ":true,"*":"image",":":false,";":false,"<":null,"=":32,">":true,"?":1,"-":[1,1,1],".":1,"@":null,"(":54927516,"A":0,"B":null,"+":64,",":29,"C":[184.438,821.61,-248.438,-850.61],"D":[0.5,0.5],"E":[0,0,0,1],"F":0,"G":[0,0,0,1],"H":[0,0],"I":null,"J":false,"K":false,"L":true,"/":null,"M":false,")":[4],"N":false},"S":{" ":true,"T":true,"U":"! .","V":[0,0,0,0],"W":0,"X":[1,1,1,1],"Y":[1,1,1,0.58824],"Z":[1,1,1,1],"[":0,"]":null,"^":0,"_":null,"`":0,"a":null,"b":0,"c":null,"d":null,"e":null},"O":{" ":true,"P":["claimButton"],"Q":{"q":{" ":true,"R":{}}}}},"___1":[195,0,198]},"! <":{"!":"Lwall","&":[]," ":true,"$":"! <","#":"!  ","'":[],"%":{},"___1":[201,0,48]},"! =":{"!":"Rwall","&":[]," ":true,"$":"! =","#":"!  ","'":[],"%":{},"___1":[204,0,48]},"! >":{"!":"lowerBound","&":[]," ":true,"$":"! >","#":"!  ","'":[],"%":{},"___1":[207,0,210]},"! ?":{"!":"platformSpawnHeight","&":[]," ":true,"$":"! ?","#":"!  ","'":[],"%":{},"___1":[213,0,6]},"! @":{"!":"killPlane","&":[]," ":true,"$":"! @","#":"!  ","'":[],"%":{},"___1":[216,0,219]},"! 0":{"!":"game","&":[]," ":true,"$":"! 0","#":"!  ","'":["! h"],"%":{"O":{" ":true,"P":[],"Q":{}}},"___2":0},"! h":{"!":"platformManager","&":[]," ":true,"$":"! h","#":"! 0","'":[],"%":{"O":{" ":true,"P":["platformManager"],"Q":{"!:":{" ":true,"R":{}}}}},"___2":0},"! d":{"!":"Text","&":[]," ":true,"$":"! d","#":"! )","'":[],"%":{"1":{"0":[0,0,1,1],"2":[1,0.5,1,0.5],"3":[1,0.5],"4":"Score 1000","5":null,"6":61051619,"7":32,"8":8,"9":32," ":true,"*":"text",":":false,";":false,"<":null,"=":32,">":true,"?":1,"-":[0.16078,0.21176,0.43529],".":1,"@":null,"(":null,"A":0,"B":null,"+":208,",":32.078,"C":[-211.112,-9.422,3.112,-22.656],"D":[1,0.5],"E":[0,0,0,1],"F":0.08,"G":[0,0,0,1],"H":[0,0],"I":null,"J":true,"K":true,"L":false,"/":null,"M":false,")":[4],"N":false}},"___1":[222,0,33]},"! f":{"!":"Text","&":[]," ":true,"$":"! f","#":"! )","'":[],"%":{"1":{"0":[0,0,1,1],"2":[1,0.5,1,0.5],"3":[1,0.5],"4":"a free pizza!","5":null,"6":61051619,"7":32,"8":8,"9":32," ":true,"*":"text",":":false,";":false,"<":null,"=":32,">":true,"?":1,"-":[0.16078,0.21176,0.43529],".":1,"@":null,"(":null,"A":0,"B":null,"+":252,",":32.078,"C":[-255.112,-22.146,3.112,-9.932],"D":[1,0.5],"E":[0,0,0,1],"F":0.08,"G":[0,0,0,1],"H":[0,0],"I":null,"J":true,"K":true,"L":false,"/":null,"M":false,")":[4],"N":false}},"___1":[225,0,33]},"! e":{"!":"Text","&":[]," ":true,"$":"! e","#":"! )","'":[],"%":{"1":{"0":[0,0,1,1],"2":[1,0.5,1,0.5],"3":[1,0.5],"4":"points to get","5":null,"6":61051619,"7":32,"8":8,"9":32," ":true,"*":"text",":":false,";":false,"<":null,"=":32,">":true,"?":1,"-":[0.16078,0.21176,0.43529],".":1,"@":null,"(":null,"A":0,"B":null,"+":248,",":32.078,"C":[-251.112,-15.826,3.112,-16.252],"D":[1,0.5],"E":[0,0,0,1],"F":0.08,"G":[0,0,0,1],"H":[0,0],"I":null,"J":true,"K":true,"L":false,"/":null,"M":false,")":[4],"N":false}},"___1":[228,0,33]},"! g":{"!":"Text","&":[]," ":true,"$":"! g","#":"! .","'":[],"%":{"1":{"0":[0,0,1,1],"2":[0.5,0.5,0.5,0.5],"3":[0.5,0.5],"4":"You won the prize!","5":null,"6":61051619,"7":4.4,"8":8,"9":32," ":true,"*":"text",":":false,";":false,"<":null,"=":32,">":true,"?":1,"-":[0.16078,0.21176,0.43529],".":1,"@":null,"(":null,"A":0,"B":null,"+":372,",":32.078,"C":[-26.156,-10.597,-26.156,6.086],"D":[0.5,0.5],"E":[0,0,0,1],"F":0,"G":[0,0,0,1],"H":[0,0],"I":null,"J":true,"K":true,"!;":"stretch","L":false,"/":null,"M":false,")":[4],"N":false}},"___1":[231,0,6]}},"checkpoint_id":"7fa9a1b7-62a9-4d9e-ba8c-70184b17a574","branch_id":"3fd76815-bef0-44fd-a317-a728799a9fe5","id":1204680,"compressedFormat":{"fieldFirstCode":32,"fieldCodeBase":95,"fieldArray":["enabled","name",1,"parent","resource_id","components","tags","children","spriteAsset","layers","type","width","height","color","opacity","batchGroupId","rect","element","anchor","pivot","text","key","fontAsset","fontSize","minFontSize","maxFontSize","autoFitWidth","autoFitHeight","maxLines","lineHeight","wrapLines","spacing","textureAsset","spriteFrame","pixelsPerUnit","margin","alignment","outlineColor","outlineThickness","shadowColor","shadowOffset","materialAsset","autoWidth","autoHeight","useInput","mask","enableMarkup","script","order","scripts","attributes","button","active","imageEntity","hitPadding","transitionMode","hoverTint","pressedTint","inactiveTint","fadeDuration",1,"hoverSpriteAsset","hoverSpriteFrame","pressedSpriteAsset","pressedSpriteFrame","inactiveSpriteAsset","inactiveSpriteFrame","hoverTextureAsset","pressedTextureAsset","inactiveTextureAsset","fps","loop","sprite","flipX","flipY","frame","speed","drawOrder","autoPlayClip","clips","resetButton","claimButton","0","1","2","iOspressFix","camera","projection","farClip","clearColorBuffer","priority","fov","clearDepthBuffer","frustumCulling","clearColor","orthoHeight","nearClip",1,"gammaCorrection","toneMapping","playerPhysicsx","playerPhysicsy","autoPlay","mainCharAnim","screen","screenSpace","scaleMode","scaleBlend","resolution","referenceResolution","scoringSystem","deathScreenDropDown","endScreenScore","endScreenHighScore","loseGroup","startGroup","startButton","leftRightGroup","moveLeftButton","moveRightButton","couponNotification","platformManager","fitMode"],"singleVecs":[0,0,0,3.5,3.5,3.5,1,1,1,0.143,0.143,0.143,250,0,0,200,0,0,150,0,0,100,0,0,50,0,0,31.12893,31.12893,31.12893,0.215,0.215,0.215,0.14532,0.14532,0.14532,90,0,0,0.02525,0.02525,0.02525,0.08033,0.08033,0.08033,1000,0,0,0.11656,0.11656,0.11656,0,0,3.90461,1.6,1.6,2,0,-0.131,0,-0.08164,0,0.01632,0.08999,0,0.01632,0,0,-1.53631,595.48237,595.48237,595.48237,0,192.25695,0,1,1.14492,1,0,-609.17346,0,1114.95773,413.88265,413.88265,18.86446,-23.35044,0,0,1300,0,0,341.3019,0,1114.95773,1500.40182,413.88265,0,466.44993,0,0.45763,0.45763,0.45763,-0.002,92.77233,0,9.30758,10.31489,10.31489,-0.001,92.77235,0,8.21668,8.21668,8.21668,0,-197.37029,0,10.9579,10.9579,10.9579,-12.454,3.16899,0,0.56072,0.56072,0.56072,-12.034,-3.90701,0,0.51575,0.51575,0.51575,33.03834,-9.65199,0,38.63504,-17.137,0,0,-19.486,0,-7.16,-19.4859,0,7.16,-19.4859,0,0.21508,0.21508,0.21508,0,-17.34641,0,-2.14998,-23.876,0,7.73814,-23.88482,0,-4.44908,-21.864,0,4.233,-21.866,0,-9.30367,-23.87782,0,-7.83024,19.6402,0,0.233,0.22307,0.22307,-19.22072,0.6539,0,0.01626,0.01626,0.01626,3.35267,-8.70333,0,0.26649,0.26649,0.26649,-3.46088,-8.703,0,0.266,0.266,0.266,0,103.62033,0,216.43801,836.10958,0,8.27694,8.27694,8.27694,-1.369,0,0,1.36924,0,0,0,-0.5358,0,0.1,0.1,0.1,0,2.53994,0,0,-0.97758,0,0.16773,0.16773,0.16773,-3.11235,6.61741,0,-3.11235,-6.10715,0,-3.11235,0.21304,0,0,-8.3414,0],"tripleVecs":[0,0,6]}}